{
  "experiment": "rendered",
  "rows": [
    {
      "N": 1,
      "experiment": "rendered_visual_simulator",
      "method": "calibrated",
      "seed": 3,
      "selected_real_utility": 0.575908203125,
      "violation_rate": 0.69140625
    },
    {
      "N": 2,
      "experiment": "rendered_visual_simulator",
      "method": "calibrated",
      "seed": 3,
      "selected_real_utility": 0.76171875,
      "violation_rate": 0.4784694881889764
    },
    {
      "N": 4,
      "experiment": "rendered_visual_simulator",
      "method": "calibrated",
      "seed": 3,
      "selected_real_utility": 0.9074833764529435,
      "violation_rate": 0.22970475956130487
    },
    {
      "N": 8,
      "experiment": "rendered_visual_simulator",
      "method": "calibrated",
      "seed": 3,
      "selected_real_utility": 0.9823953007656374,
      "violation_rate": 0.053305256153573184
    },
    {
      "N": 16,
      "experiment": "rendered_visual_simulator",
      "method": "calibrated",
      "seed": 3,
      "selected_real_utility": 0.9992318692544736,
      "violation_rate": 0.0028279963780460855
    },
    {
      "N": 32,
      "experiment": "rendered_visual_simulator",
      "method": "calibrated",
      "seed": 3,
      "selected_real_utility": 0.9999989148882922,
      "violation_rate": 4.997216659794747e-06
    },
    {
      "N": 64,
      "experiment": "rendered_visual_simulator",
      "method": "calibrated",
      "seed": 3,
      "selected_real_utility": 0.9999999999999799,
      "violation_rate": 1.218813507558315e-13
    },
    {
      "N": 128,
      "experiment": "rendered_visual_simulator",
      "method": "calibrated",
      "seed": 3,
      "selected_real_utility": 1.0,
      "violation_rate": 0.0
    },
    {
      "N": 1,
      "experiment": "rendered_visual_simulator",
      "method": "grounded_combined",
      "seed": 3,
      "selected_real_utility": 0.575908203125,
      "violation_rate": 0.69140625
    },
    {
      "N": 2,
      "experiment": "rendered_visual_simulator",
      "method": "grounded_combined",
      "seed": 3,
      "selected_real_utility": 0.7216635396161417,
      "violation_rate": 0.4784694881889764
    },
    {
      "N": 4,
      "experiment": "rendered_visual_simulator",
      "method": "grounded_combined",
      "seed": 3,
      "selected_real_utility": 0.8759772076537309,
      "violation_rate": 0.22970475956130487
    },
    {
      "N": 8,
      "experiment": "rendered_visual_simulator",
      "method": "grounded_combined",
      "seed": 3,
      "selected_real_utility": 0.9722485765589113,
      "violation_rate": 0.053305256153573184
    },
    {
      "N": 16,
      "experiment": "rendered_visual_simulator",
      "method": "grounded_combined",
      "seed": 3,
      "selected_real_utility": 0.9985787622746001,
      "violation_rate": 0.002827996378046086
    },
    {
      "N": 32,
      "experiment": "rendered_visual_simulator",
      "method": "grounded_combined",
      "seed": 3,
      "selected_real_utility": 0.9999975995332334,
      "violation_rate": 4.997216659794747e-06
    },
    {
      "N": 64,
      "experiment": "rendered_visual_simulator",
      "method": "grounded_combined",
      "seed": 3,
      "selected_real_utility": 0.9999999999999359,
      "violation_rate": 1.218813507558315e-13
    },
    {
      "N": 128,
      "experiment": "rendered_visual_simulator",
      "method": "grounded_combined",
      "seed": 3,
      "selected_real_utility": 1.0,
      "violation_rate": 0.0
    },
    {
      "N": 1,
      "experiment": "rendered_visual_simulator",
      "method": "oracle",
      "seed": 3,
      "selected_real_utility": 0.575908203125,
      "violation_rate": 0.69140625
    },
    {
      "N": 2,
      "experiment": "rendered_visual_simulator",
      "method": "oracle",
      "seed": 3,
      "selected_real_utility": 0.7628574064960632,
      "violation_rate": 0.4784694881889764
    },
    {
      "N": 4,
      "experiment": "rendered_visual_simulator",
      "method": "oracle",
      "seed": 3,
      "selected_real_utility": 0.9083921215316836,
      "violation_rate": 0.22970475956130484
    },
    {
      "N": 8,
      "experiment": "rendered_visual_simulator",
      "method": "oracle",
      "seed": 3,
      "selected_real_utility": 0.9826973846568683,
      "violation_rate": 0.05330525615357319
    },
    {
      "N": 16,
      "experiment": "rendered_visual_simulator",
      "method": "oracle",
      "seed": 3,
      "selected_real_utility": 0.9992543879731663,
      "violation_rate": 0.002827996378046086
    },
    {
      "N": 32,
      "experiment": "rendered_visual_simulator",
      "method": "oracle",
      "seed": 3,
      "selected_real_utility": 0.9999989505182298,
      "violation_rate": 4.997216659794746e-06
    },
    {
      "N": 64,
      "experiment": "rendered_visual_simulator",
      "method": "oracle",
      "seed": 3,
      "selected_real_utility": 0.9999999999999802,
      "violation_rate": 1.2188135075583147e-13
    },
    {
      "N": 128,
      "experiment": "rendered_visual_simulator",
      "method": "oracle",
      "seed": 3,
      "selected_real_utility": 1.0,
      "violation_rate": 0.0
    },
    {
      "N": 1,
      "experiment": "rendered_visual_simulator",
      "method": "random",
      "seed": 3,
      "selected_real_utility": 0.575908203125,
      "violation_rate": 0.69140625
    },
    {
      "N": 2,
      "experiment": "rendered_visual_simulator",
      "method": "random",
      "seed": 3,
      "selected_real_utility": 0.583982375738189,
      "violation_rate": 0.6802257627952757
    },
    {
      "N": 4,
      "experiment": "rendered_visual_simulator",
      "method": "random",
      "seed": 3,
      "selected_real_utility": 0.5802078687429697,
      "violation_rate": 0.6820221105174353
    },
    {
      "N": 8,
      "experiment": "rendered_visual_simulator",
      "method": "random",
      "seed": 3,
      "selected_real_utility": 0.5712631294768546,
      "violation_rate": 0.6954643374422196
    },
    {
      "N": 16,
      "experiment": "rendered_visual_simulator",
      "method": "random",
      "seed": 3,
      "selected_real_utility": 0.5600627637029367,
      "violation_rate": 0.7181870733145095
    },
    {
      "N": 32,
      "experiment": "rendered_visual_simulator",
      "method": "random",
      "seed": 3,
      "selected_real_utility": 0.5448194381709085,
      "violation_rate": 0.7518176682570995
    },
    {
      "N": 64,
      "experiment": "rendered_visual_simulator",
      "method": "random",
      "seed": 3,
      "selected_real_utility": 0.5123161935303933,
      "violation_rate": 0.8079591883559052
    },
    {
      "N": 128,
      "experiment": "rendered_visual_simulator",
      "method": "random",
      "seed": 3,
      "selected_real_utility": 0.46125000000000005,
      "violation_rate": 0.875
    },
    {
      "N": 1,
      "experiment": "rendered_visual_simulator",
      "method": "raw_semantic",
      "seed": 3,
      "selected_real_utility": 0.575908203125,
      "violation_rate": 0.69140625
    },
    {
      "N": 2,
      "experiment": "rendered_visual_simulator",
      "method": "raw_semantic",
      "seed": 3,
      "selected_real_utility": 0.5873089936023622,
      "violation_rate": 0.7186423474409449
    },
    {
      "N": 4,
      "experiment": "rendered_visual_simulator",
      "method": "raw_semantic",
      "seed": 3,
      "selected_real_utility": 0.5334499954302587,
      "violation_rate": 0.861218023528309
    },
    {
      "N": 8,
      "experiment": "rendered_visual_simulator",
      "method": "raw_semantic",
      "seed": 3,
      "selected_real_utility": 0.47959653457676654,
      "violation_rate": 0.9743301118164205
    },
    {
      "N": 16,
      "experiment": "rendered_visual_simulator",
      "method": "raw_semantic",
      "seed": 3,
      "selected_real_utility": 0.47026644936838713,
      "violation_rate": 0.9991551112182726
    },
    {
      "N": 32,
      "experiment": "rendered_visual_simulator",
      "method": "raw_semantic",
      "seed": 3,
      "selected_real_utility": 0.4779195372692561,
      "violation_rate": 0.9999993024587355
    },
    {
      "N": 64,
      "experiment": "rendered_visual_simulator",
      "method": "raw_semantic",
      "seed": 3,
      "selected_real_utility": 0.4924750104774114,
      "violation_rate": 0.9999999999999957
    },
    {
      "N": 128,
      "experiment": "rendered_visual_simulator",
      "method": "raw_semantic",
      "seed": 3,
      "selected_real_utility": 0.50875,
      "violation_rate": 1.0
    },
    {
      "N": 1,
      "experiment": "rendered_visual_simulator",
      "method": "semantic_plus_physical",
      "seed": 3,
      "selected_real_utility": 0.575908203125,
      "violation_rate": 0.69140625
    },
    {
      "N": 2,
      "experiment": "rendered_visual_simulator",
      "method": "semantic_plus_physical",
      "seed": 3,
      "selected_real_utility": 0.7212355437992126,
      "violation_rate": 0.47846948818897633
    },
    {
      "N": 4,
      "experiment": "rendered_visual_simulator",
      "method": "semantic_plus_physical",
      "seed": 3,
      "selected_real_utility": 0.8758548757967755,
      "violation_rate": 0.22970475956130482
    },
    {
      "N": 8,
      "experiment": "rendered_visual_simulator",
      "method": "semantic_plus_physical",
      "seed": 3,
      "selected_real_utility": 0.9722395618266899,
      "violation_rate": 0.053305256153573184
    },
    {
      "N": 16,
      "experiment": "rendered_visual_simulator",
      "method": "semantic_plus_physical",
      "seed": 3,
      "selected_real_utility": 0.9985787540273228,
      "violation_rate": 0.002827996378046086
    },
    {
      "N": 32,
      "experiment": "rendered_visual_simulator",
      "method": "semantic_plus_physical",
      "seed": 3,
      "selected_real_utility": 0.9999975995332333,
      "violation_rate": 4.997216659794746e-06
    },
    {
      "N": 64,
      "experiment": "rendered_visual_simulator",
      "method": "semantic_plus_physical",
      "seed": 3,
      "selected_real_utility": 0.9999999999999359,
      "violation_rate": 1.218813507558315e-13
    },
    {
      "N": 128,
      "experiment": "rendered_visual_simulator",
      "method": "semantic_plus_physical",
      "seed": 3,
      "selected_real_utility": 1.0,
      "violation_rate": 0.0
    },
    {
      "N": 1,
      "experiment": "rendered_visual_simulator",
      "method": "torch_calibrated",
      "seed": 3,
      "selected_real_utility": 0.575908203125,
      "violation_rate": 0.69140625
    },
    {
      "N": 2,
      "experiment": "rendered_visual_simulator",
      "method": "torch_calibrated",
      "seed": 3,
      "selected_real_utility": 0.7616930671751969,
      "violation_rate": 0.4784694881889764
    },
    {
      "N": 4,
      "experiment": "rendered_visual_simulator",
      "method": "torch_calibrated",
      "seed": 3,
      "selected_real_utility": 0.9074745920041245,
      "violation_rate": 0.22970475956130487
    },
    {
      "N": 8,
      "experiment": "rendered_visual_simulator",
      "method": "torch_calibrated",
      "seed": 3,
      "selected_real_utility": 0.9823923790009026,
      "violation_rate": 0.053305256153573184
    },
    {
      "N": 16,
      "experiment": "rendered_visual_simulator",
      "method": "torch_calibrated",
      "seed": 3,
      "selected_real_utility": 0.9992321855681114,
      "violation_rate": 0.002827996378046086
    },
    {
      "N": 32,
      "experiment": "rendered_visual_simulator",
      "method": "torch_calibrated",
      "seed": 3,
      "selected_real_utility": 0.9999989172387633,
      "violation_rate": 4.997216659794747e-06
    },
    {
      "N": 64,
      "experiment": "rendered_visual_simulator",
      "method": "torch_calibrated",
      "seed": 3,
      "selected_real_utility": 0.99999999999998,
      "violation_rate": 1.218813507558315e-13
    },
    {
      "N": 128,
      "experiment": "rendered_visual_simulator",
      "method": "torch_calibrated",
      "seed": 3,
      "selected_real_utility": 1.0,
      "violation_rate": 0.0
    },
    {
      "N": 1,
      "experiment": "rendered_visual_simulator",
      "method": "torch_semantic",
      "seed": 3,
      "selected_real_utility": 0.575908203125,
      "violation_rate": 0.69140625
    },
    {
      "N": 2,
      "experiment": "rendered_visual_simulator",
      "method": "torch_semantic",
      "seed": 3,
      "selected_real_utility": 0.5800859682578741,
      "violation_rate": 0.7245939960629921
    },
    {
      "N": 4,
      "experiment": "rendered_visual_simulator",
      "method": "torch_semantic",
      "seed": 3,
      "selected_real_utility": 0.5207980684055119,
      "violation_rate": 0.8666599643794526
    },
    {
      "N": 8,
      "experiment": "rendered_visual_simulator",
      "method": "torch_semantic",
      "seed": 3,
      "selected_real_utility": 0.4675204350239986,
      "violation_rate": 0.975390531786059
    },
    {
      "N": 16,
      "experiment": "rendered_visual_simulator",
      "method": "torch_semantic",
      "seed": 3,
      "selected_real_utility": 0.4599297719576574,
      "violation_rate": 0.9991931741766756
    },
    {
      "N": 32,
      "experiment": "rendered_visual_simulator",
      "method": "torch_semantic",
      "seed": 3,
      "selected_real_utility": 0.4684742922036743,
      "violation_rate": 0.9999994346168277
    },
    {
      "N": 64,
      "experiment": "rendered_visual_simulator",
      "method": "torch_semantic",
      "seed": 3,
      "selected_real_utility": 0.47242223496389313,
      "violation_rate": 0.9999999999999984
    },
    {
      "N": 128,
      "experiment": "rendered_visual_simulator",
      "method": "torch_semantic",
      "seed": 3,
      "selected_real_utility": 0.46375000000000005,
      "violation_rate": 1.0
    }
  ],
  "seed": 3
}